multibodypendulum/__init__.py
multibodypendulum/npendul.py
multibodypendulum-0.2.4.dist-info/LICENSE
multibodypendulum-0.2.4.dist-info/METADATA
multibodypendulum-0.2.4.dist-info/WHEEL
multibodypendulum-0.2.4.dist-info/RECORD
