Metadata-Version: 2.1
Name: multibodypendulum
Version: 0.2.4
Summary: Simulates a multi-body-pendulum
License: MIT
Author: Tue Boesen
Author-email: tue.boesen@protonmail.com
Requires-Python: >=3.10
Classifier: License :: OSI Approved :: MIT License
Classifier: Programming Language :: Python :: 3
Classifier: Programming Language :: Python :: 3.10
Classifier: Programming Language :: Python :: 3.11
Classifier: Programming Language :: Python :: 3.12
Requires-Dist: matplotlib (>=3.7.1)
Requires-Dist: numpy (>=1.24.2)
Requires-Dist: torch (>=1.5)
